optalgotools/__init__.py
optalgotools/routing.py
optalgotools/structures.py
optalgotools/utilities.py
optalgotools/algorithms/__init__.py
optalgotools/algorithms/_sa.py
optalgotools/algorithms/_ts.py
optalgotools/algorithms/graph_search.py
optalgotools/problems/__init__.py
optalgotools/problems/__problem_base.py
optalgotools/problems/albp.py
optalgotools/problems/sheets.py
optalgotools/problems/sudoku.py
optalgotools/problems/tsp.py
optalgotools-1.0.0.dist-info/LICENSE
optalgotools-1.0.0.dist-info/METADATA
optalgotools-1.0.0.dist-info/WHEEL
optalgotools-1.0.0.dist-info/top_level.txt
optalgotools-1.0.0.dist-info/RECORD
